datahider/__init__.py
datahider/tests/test_data_hider.py
datahider-0.4.dist-info/METADATA
datahider-0.4.dist-info/WHEEL
datahider-0.4.dist-info/RECORD
