Metadata-Version: 2.1
Name: datahider
Version: 0.4
Summary: Facade that handles encryption and decryption of dictionaries using a private key from AWS secret store.
License: Proprietary
Author: Michael Roeleveld
Author-email: m.roeleveld@avon-apps.nl
Requires-Python: >=3.10
Classifier: License :: Other/Proprietary License
Classifier: Programming Language :: Python :: 3
Classifier: Programming Language :: Python :: 3.10
Classifier: Programming Language :: Python :: 3.11
Classifier: Programming Language :: Python :: 3.12
Requires-Dist: cryptography (>=41.0.0)
Requires-Dist: pytest (>=7.4.4)
